pta_reload/__init__.py
pta_reload/ta.py
pta_reload/momentum/cmo.py
pta_reload/momentum/macd.py
pta_reload/momentum/mom.py
pta_reload/momentum/roc.py
pta_reload/momentum/rsi.py
pta_reload/momentum/stoch.py
pta_reload/momentum/willr.py
pta_reload/overlap/alma.py
pta_reload/overlap/dema.py
pta_reload/overlap/ema.py
pta_reload/overlap/fwma.py
pta_reload/overlap/hilo.py
pta_reload/overlap/hl2.py
pta_reload/overlap/hlc3.py
pta_reload/overlap/hma.py
pta_reload/overlap/hwma.py
pta_reload/overlap/ichimoku.py
pta_reload/overlap/jma.py
pta_reload/overlap/kama.py
pta_reload/overlap/linreg.py
pta_reload/overlap/ma.py
pta_reload/overlap/mcgd.py
pta_reload/overlap/midpoint.py
pta_reload/overlap/midprice.py
pta_reload/overlap/ohlc4.py
pta_reload/overlap/pwma.py
pta_reload/overlap/rma.py
pta_reload/overlap/sinwma.py
pta_reload/overlap/sma.py
pta_reload/overlap/ssf.py
pta_reload/overlap/supertrend.py
pta_reload/overlap/swma.py
pta_reload/overlap/t3.py
pta_reload/overlap/tema.py
pta_reload/overlap/trima.py
pta_reload/overlap/vidya.py
pta_reload/overlap/vwap.py
pta_reload/overlap/vwma.py
pta_reload/overlap/wcp.py
pta_reload/overlap/wma.py
pta_reload/overlap/zlma.py
pta_reload/statistics/stdev.py
pta_reload/statistics/variance.py
pta_reload/trend/adx.py
pta_reload/trend/aroon.py
pta_reload/trend/psar.py
pta_reload/utils/__init__.py
pta_reload/utils/_candles.py
pta_reload/utils/_core.py
pta_reload/utils/_math.py
pta_reload/utils/_signals.py
pta_reload/utils/_time.py
pta_reload/utils/constant.py
pta_reload/volatility/atr.py
pta_reload/volatility/bbands.py
pta_reload/volatility/kc.py
pta_reload/volatility/true_range.py
pta_reload/volume/obv.py
pta_reload-1.0.2.dist-info/METADATA
pta_reload-1.0.2.dist-info/WHEEL
pta_reload-1.0.2.dist-info/top_level.txt
pta_reload-1.0.2.dist-info/RECORD
