Metadata-Version: 2.4
Name: pta_reload
Version: 1.0.2
Author: Thinh Vu
Author-email: mrthinh@live.com
Maintainer: Thinh Vu
Maintainer-email: mrthinh@live.com
Requires-Dist: numpy<=1.26.4
Requires-Dist: pandas
Provides-Extra: dev
Requires-Dist: matplotlib; extra == "dev"
Requires-Dist: mplfinance; extra == "dev"
Requires-Dist: scipy; extra == "dev"
Requires-Dist: sklearn; extra == "dev"
Requires-Dist: statsmodels; extra == "dev"
Requires-Dist: stochastic; extra == "dev"
Requires-Dist: tqdm; extra == "dev"
Dynamic: author
Dynamic: author-email
Dynamic: maintainer
Dynamic: maintainer-email
Dynamic: provides-extra
Dynamic: requires-dist
